Workbook

Sheet Commandes
A1: n_commande | B1: date_commande | C1: date_livraison | D1: client_id | E1: ville | F1: agence_id | G1: commercial_id | H1: produit_id | I1: quantite | J1: prix_unitaire_ht | K1: remise | L1: ca_ht | M1: facturee | N1: annee | O1: region | P1: categorie | Q1: cout | R1: marge | S1: delai_ouvre | T1: date_promise | U1: en_retard
A2: C-11615 | B2: 46295 | C2: 46296 | D2: CL056 | E2: Tourcoing | F2: AG01 | G2: C01 | H2: P036 | I2: 1 | J2: 290 | K2: 0.08 | L2: 266.8 | M2: FALSE | N2: =YEAR(B2) -> 2026 | O2: =INDEX(Agences!$C:$C,MATCH(F2,Agences!$A:$A,0)) -> Nord | P2: =INDEX(Produits!$C:$C,MATCH(H2,Produits!$A:$A,0)) -> Maintenance | Q2: =I2*INDEX(Produits!$E:$E,MATCH(H2,Produits!$A:$A,0)) -> 139.2 | R2: =L2-Q2 -> 127.6 | S2: =NETWORKDAYS(B2,C2)-1 -> 1 | T2: =WORKDAY(B2,5) -> 46302 | U2: =C2>T2 -> FALSE
A3: C-11615 | B3: 46295 | C3: 46296 | D3: CL056 | E3: Tourcoing | F3: AG01 | G3: C01 | H3: P011 | I3: 7 | J3: 310 | K3: 0 | L3: 2170 | M3: FALSE | N3: =YEAR(B3) -> 2026 | O3: =INDEX(Agences!$C:$C,MATCH(F3,Agences!$A:$A,0)) -> Nord | P3: =INDEX(Produits!$C:$C,MATCH(H3,Produits!$A:$A,0)) -> Mobilier | Q3: =I3*INDEX(Produits!$E:$E,MATCH(H3,Produits!$A:$A,0)) -> 1302 | R3: =L3-Q3 -> 868 | S3: =NETWORKDAYS(B3,C3)-1 -> 1 | T3: =WORKDAY(B3,5) -> 46302 | U3: =C3>T3 -> FALSE
A4: C-11589 | B4: 46295 | C4: 46296 | D4: CL436 | E4: Saint-Malo | F4: AG06 | G4: C16 | H4: P018 | I4: 2 | J4: 219 | K4: 0.05 | L4: 416.1 | M4: FALSE | N4: =YEAR(B4) -> 2026 | O4: =INDEX(Agences!$C:$C,MATCH(F4,Agences!$A:$A,0)) -> Ouest | P4: =INDEX(Produits!$C:$C,MATCH(H4,Produits!$A:$A,0)) -> Informatique | Q4: =I4*INDEX(Produits!$E:$E,MATCH(H4,Produits!$A:$A,0)) -> 359.16 | R4: =L4-Q4 -> 56.94 | S4: =NETWORKDAYS(B4,C4)-1 -> 1 | T4: =WORKDAY(B4,5) -> 46302 | U4: =C4>T4 -> FALSE
A5: C-11589 | B5: 46295 | C5: 46296 | D5: CL436 | E5: Saint-Malo | F5: AG06 | G5: C16 | H5: P024 | I5: 1 | J5: 340 | K5: 0.08 | L5: 312.8 | M5: FALSE | N5: =YEAR(B5) -> 2026 | O5: =INDEX(Agences!$C:$C,MATCH(F5,Agences!$A:$A,0)) -> Ouest | P5: =INDEX(Produits!$C:$C,MATCH(H5,Produits!$A:$A,0)) -> Informatique | Q5: =I5*INDEX(Produits!$E:$E,MATCH(H5,Produits!$A:$A,0)) -> 275.4 | R5: =L5-Q5 -> 37.4 | S5: =NETWORKDAYS(B5,C5)-1 -> 1 | T5: =WORKDAY(B5,5) -> 46302 | U5: =C5>T5 -> FALSE
A6: C-11589 | B6: 46295 | C6: 46296 | D6: CL436 | E6: Saint-Malo | F6: AG06 | G6: C16 | H6: P004 | I6: 2 | J6: 79 | K6: 0.08 | L6: 145.36 | M6: FALSE | N6: =YEAR(B6) -> 2026 | O6: =INDEX(Agences!$C:$C,MATCH(F6,Agences!$A:$A,0)) -> Ouest | P6: =INDEX(Produits!$C:$C,MATCH(H6,Produits!$A:$A,0)) -> Mobilier | Q6: =I6*INDEX(Produits!$E:$E,MATCH(H6,Produits!$A:$A,0)) -> 93.22 | R6: =L6-Q6 -> 52.14 | S6: =NETWORKDAYS(B6,C6)-1 -> 1 | T6: =WORKDAY(B6,5) -> 46302 | U6: =C6>T6 -> FALSE
A7: C-11616 | B7: 46295 | C7: 46297 | D7: CL040 | E7: Pessac | F7: AG07 | G7: C20 | H7: P015 | I7: 3 | J7: 790 | K7: 0.05 | L7: 2251.5 | M7: FALSE | N7: =YEAR(B7) -> 2026 | O7: =INDEX(Agences!$C:$C,MATCH(F7,Agences!$A:$A,0)) -> Sud-Ouest | P7: =INDEX(Produits!$C:$C,MATCH(H7,Produits!$A:$A,0)) -> Informatique | Q7: =I7*INDEX(Produits!$E:$E,MATCH(H7,Produits!$A:$A,0)) -> 1730.1 | R7: =L7-Q7 -> 521.4 | S7: =NETWORKDAYS(B7,C7)-1 -> 2 | T7: =WORKDAY(B7,5) -> 46302 | U7: =C7>T7 -> FALSE
A8: C-11616 | B8: 46295 | C8: 46297 | D8: CL040 | E8: Pessac | F8: AG07 | G8: C20 | H8: P039 | I8: 1 | J8: 55 | K8: 0 | L8: 55 | M8: FALSE | N8: =YEAR(B8) -> 2026 | O8: =INDEX(Agences!$C:$C,MATCH(F8,Agences!$A:$A,0)) -> Sud-Ouest | P8: =INDEX(Produits!$C:$C,MATCH(H8,Produits!$A:$A,0)) -> Maintenance | Q8: =I8*INDEX(Produits!$E:$E,MATCH(H8,Produits!$A:$A,0)) -> 24.75 | R8: =L8-Q8 -> 30.25 | S8: =NETWORKDAYS(B8,C8)-1 -> 2 | T8: =WORKDAY(B8,5) -> 46302 | U8: =C8>T8 -> FALSE
A9: C-11617 | B9: 46295 | C9: 46297 | D9: CL379 | E9: Lyon | F9: AG11 | G9: C33 | H9: P007 | I9: 1 | J9: 165 | K9: 0 | L9: 165 | M9: FALSE | N9: =YEAR(B9) -> 2026 | O9: =INDEX(Agences!$C:$C,MATCH(F9,Agences!$A:$A,0)) -> Est | P9: =INDEX(Produits!$C:$C,MATCH(H9,Produits!$A:$A,0)) -> Mobilier | Q9: =I9*INDEX(Produits!$E:$E,MATCH(H9,Produits!$A:$A,0)) -> 107.25 | R9: =L9-Q9 -> 57.75 | S9: =NETWORKDAYS(B9,C9)-1 -> 2 | T9: =WORKDAY(B9,5) -> 46302 | U9: =C9>T9 -> FALSE
A10: C-11617 | B10: 46295 | C10: 46297 | D10: CL379 | E10: Lyon | F10: AG11 | G10: C33 | H10: P035 | I10: 1 | J10: 120 | K10: 0 | L10: 120 | M10: FALSE | N10: =YEAR(B10) -> 2026 | O10: =INDEX(Agences!$C:$C,MATCH(F10,Agences!$A:$A,0)) -> Est | P10: =INDEX(Produits!$C:$C,MATCH(H10,Produits!$A:$A,0)) -> Maintenance | Q10: =I10*INDEX(Produits!$E:$E,MATCH(H10,Produits!$A:$A,0)) -> 55.2 | R10: =L10-Q10 -> 64.8 | S10: =NETWORKDAYS(B10,C10)-1 -> 2 | T10: =WORKDAY(B10,5) -> 46302 | U10: =C10>T10 -> FALSE
A11: C-11617 | B11: 46295 | C11: 46297 | D11: CL379 | E11: Lyon | F11: AG11 | G11: C33 | H11: P021 | I11: 3 | J11: 69 | K11: 0 | L11: 207 | M11: FALSE | N11: =YEAR(B11) -> 2026 | O11: =INDEX(Agences!$C:$C,MATCH(F11,Agences!$A:$A,0)) -> Est | P11: =INDEX(Produits!$C:$C,MATCH(H11,Produits!$A:$A,0)) -> Informatique | Q11: =I11*INDEX(Produits!$E:$E,MATCH(H11,Produits!$A:$A,0)) -> 163.53 | R11: =L11-Q11 -> 43.47 | S11: =NETWORKDAYS(B11,C11)-1 -> 2 | T11: =WORKDAY(B11,5) -> 46302 | U11: =C11>T11 -> FALSE
A12: C-11617 | B12: 46295 | C12: 46297 | D12: CL379 | E12: Lyon | F12: AG11 | G12: C33 | H12: P040 | I12: 1 | J12: 180 | K12: 0.08 | L12: 165.6 | M12: FALSE | N12: =YEAR(B12) -> 2026 | O12: =INDEX(Agences!$C:$C,MATCH(F12,Agences!$A:$A,0)) -> Est | P12: =INDEX(Produits!$C:$C,MATCH(H12,Produits!$A:$A,0)) -> Maintenance | Q12: =I12*INDEX(Produits!$E:$E,MATCH(H12,Produits!$A:$A,0)) -> 82.8 | R12: =L12-Q12 -> 82.8 | S12: =NETWORKDAYS(B12,C12)-1 -> 2 | T12: =WORKDAY(B12,5) -> 46302 | U12: =C12>T12 -> FALSE
A13: C-11618 | B13: 46295 | C13: 46304 | D13: CL380 | E13: Colmar | F13: AG12 | G13: C36 | H13: P007 | I13: 1 | J13: 165 | K13: 0 | L13: 165 | M13: FALSE | N13: =YEAR(B13) -> 2026 | O13: =INDEX(Agences!$C:$C,MATCH(F13,Agences!$A:$A,0)) -> Est | P13: =INDEX(Produits!$C:$C,MATCH(H13,Produits!$A:$A,0)) -> Mobilier | Q13: =I13*INDEX(Produits!$E:$E,MATCH(H13,Produits!$A:$A,0)) -> 107.25 | R13: =L13-Q13 -> 57.75 | S13: =NETWORKDAYS(B13,C13)-1 -> 7 | T13: =WORKDAY(B13,5) -> 46302 | U13: =C13>T13 -> TRUE
... A4039: C-10003 | B4039: 45659 | C4039: 45665 | D4039: CL228 | E4039: Mulhouse | F4039: AG12 | G4039: C34 | H4039: P018 | I4039: 3 | J4039: 219 | K4039: 0.08 | L4039: 604.44 | M4039: TRUE | N4039: =YEAR(B4039) -> 2025 | O4039: =INDEX(Agences!$C:$C,MATCH(F4039,Agences!$A:$A,0)) -> Est | P4039: =INDEX(Produits!$C:$C,MATCH(H4039,Produits!$A:$A,0)) -> Informatique | Q4039: =I4039*INDEX(Produits!$E:$E,MATCH(H4039,Produits!$A:$A,0)) -> 538.74 | R4039: =L4039-Q4039 -> 65.7 | S4039: =NETWORKDAYS(B4039,C4039)-1 -> 4 | T4039: =WORKDAY(B4039,5) -> 45666 | U4039: =C4039>T4039 -> FALSE

Sheet Quarantaine
A1: n_commande | B1: date_commande | C1: date_livraison | D1: client_id | E1: ville | F1: agence_id | G1: commercial_id | H1: produit_id | I1: quantite | J1: prix_unitaire_ht | K1: remise | L1: ca_ht | M1: facturee | N1: motif
A2: C-10011 | B2: 45664 | C2: 45658 | D2: CL155 | E2: Nantes | F2: AG05 | G2: C15 | H2: P026 | I2: 5 | J2: 14.9 | K2: 0 | L2: 74.5 | M2: TRUE | N2: Livraison antérieure à la commande
A3: C-10052 | B3: 45679 | C3: 45681 | D3: CL492 | E3: Versailles | F3: AG04 | G3: C11 | H3: P051 | I3: 3 | J3: 165 | K3: 0 | L3: 495 | M3: TRUE | N3: Produit absent du référentiel
A4: C-10083 | B4: 02/03/25 | C4: 45692 | D4: CL486 | E4: Marseille | F4: AG09 | G4: C27 | H4: P039 | I4: 1 | J4: 55 | K4: 0 | L4: 55 | M4: TRUE | N4: Date au format inconnu
A5: C-10098 | B5: 45694 | C5: 45699 | D5: CL160 | E5: Vénissieux | F5: AG11 | G5: C32 | H5: P047 | I5: 1 | J5: 129 | K5: 0.02 | L5: 126.42 | M5: TRUE | N5: Produit absent du référentiel
A6: C-10120 | B6: 45702 | C6: 45708 | D6: CL425 | E6: Évreux | F6: AG02 | H6: P021 | I6: 2 | J6: 69 | K6: 0.02 | L6: 135.24 | M6: TRUE | N6: Commercial non renseigné
A7: C-10122 | B7: 45702 | C7: 45709 | D7: CL158 | E7: Nanterre | F7: AG04 | G7: C10 | H7: P039 | I7: -3 | J7: 55 | K7: 0 | L7: -165 | M7: TRUE | N7: Quantité négative
A8: C-10127 | B8: 45702 | C8: 45707 | D8: CL107 | E8: Villeurbanne | F8: AG11 | G8: C32 | H8: P025 | I8: 5 | J8: 275 | K8: 0 | L8: 1375 | M8: TRUE | N8: Prix unitaire dix fois le prix catalogue
A9: C-10173 | B9: 03/05/25 | C9: 45722 | D9: CL410 | E9: Bordeaux | F9: AG07 | G9: C19 | H9: P012 | I9: 1 | J9: 49 | K9: 0 | L9: 49 | M9: TRUE | N9: Date au format inconnu
A10: C-10174 | B10: 45721 | C10: 45716 | D10: CL070 | E10: Lyon | F10: AG11 | G10: C32 | H10: P011 | I10: 6 | J10: 310 | K10: 0.05 | L10: 1767 | M10: TRUE | N10: Livraison antérieure à la commande
A11: C-10195 | B11: 45730 | C11: 45735 | D11: CL144 | E11: Lille | F11: AG01 | G11: C01 | H11: P040 | I11: -1 | J11: 180 | K11: 0 | L11: -180 | M11: TRUE | N11: Quantité négative
A12: C-10207 | B12: 45734 | C12: 45737 | D12: CL138 | E12: Blagnac | F12: AG08 | G12: C23 | H12: P023 | I12: -2 | J12: 99 | K12: 0.02 | L12: -194.04 | M12: TRUE | N12: Quantité négative
A13: C-10251 | B13: 04/02/25 | C13: 45756 | D13: CL534 | E13: Marseille | F13: AG09 | G13: C27 | H13: P018 | I13: 2 | J13: 219 | K13: 0 | L13: 438 | M13: TRUE | N13: Date au format inconnu
A14: C-10390 | B14: 45805 | C14: 45806 | D14: CL397 | E14: Versailles | F14: AG04 | G14: C11 | H14: P051 | I14: 3 | J14: 420 | K14: 0.08 | L14: 1159.2 | M14: TRUE | N14: Produit absent du référentiel
A15: C-10404 | B15: 45810 | C15: 45813 | D15: CL324 | E15: Lyon | F15: AG11 | H15: P034 | I15: 25 | J15: 24.5 | K15: 0.1 | L15: 551.25 | M15: TRUE | N15: Commercial non renseigné
A16: C-10412 | B16: 45813 | C16: 45810 | D16: CL120 | E16: Le Havre | F16: AG02 | G16: C06 | H16: P004 | I16: 3 | J16: 79 | K16: 0 | L16: 237 | M16: TRUE | N16: Livraison antérieure à la commande
A17: C-10413 | B17: 45814 | C17: 45817 | D17: CL276 | E17: Tourcoing | F17: AG01 | H17: P007 | I17: 2 | J17: 165 | K17: 0.02 | L17: 323.4 | M17: TRUE | N17: Commercial non renseigné
A18: C-10421 | B18: 06/09/25 | C18: 45820 | D18: CL106 | E18: Versailles | F18: AG04 | G18: C10 | H18: P020 | I18: 3 | J18: 790 | K18: 0.02 | L18: 2322.6 | M18: TRUE | N18: Date au format inconnu
A19: C-10434 | B19: 45821 | C19: 45812 | D19: CL515 | E19: Dieppe | F19: AG02 | G19: C04 | H19: P004 | I19: 2 | J19: 79 | K19: 0.02 | L19: 154.84 | M19: TRUE | N19: Livraison antérieure à la commande
A20: C-10471 | B20: 45838 | C20: 45833 | D20: CL332 | E20: Pessac | F20: AG07 | G20: C20 | H20: P039 | I20: 1 | J20: 55 | K20: 0.05 | L20: 52.25 | M20: TRUE | N20: Livraison antérieure à la commande
A21: C-10502 | B21: 45848 | C21: 45852 | D21: CL447 | E21: Douai | F21: AG01 | H21: P016 | I21: 2 | J21: 179 | K21: 0.05 | L21: 340.1 | M21: TRUE | N21: Commercial non renseigné
A22: C-10558 | B22: 45880 | C22: 45877 | D22: CL392 | E22: Cholet | F22: AG05 | G22: C13 | H22: P034 | I22: 5 | J22: 24.5 | K22: 0.02 | L22: 120.05 | M22: TRUE | N22: Livraison antérieure à la commande
A23: C-10569 | B23: 45884 | C23: 45883 | D23: CL456 | E23: Saint-Malo | F23: AG06 | G23: C17 | H23: P039 | I23: 2 | J23: 55 | K23: 0 | L23: 110 | M23: TRUE | N23: Livraison antérieure à la commande
A24: C-10615 | B24: 09/05/25 | C24: 45909 | D24: CL457 | E24: Douai | F24: AG01 | G24: C01 | H24: P028 | I24: 5 | J24: 39.9 | K24: 0 | L24: 199.5 | M24: TRUE | N24: Date au format inconnu
A25: C-10666 | B25: 45925 | C25: 45929 | D25: CL222 | E25: Toulouse | F25: AG08 | G25: C23 | H25: P030 | I25: 5 | J25: 185 | K25: 0 | L25: 925 | M25: TRUE | N25: Prix unitaire dix fois le prix catalogue
A26: C-10676 | B26: 45929 | C26: 45930 | D26: CL029 | E26: Nanterre | F26: AG04 | G26: C12 | H26: P032 | I26: 5 | J26: 229 | K26: 0 | L26: 1145 | M26: TRUE | N26: Prix unitaire dix fois le prix catalogue
A27: C-10700 | B27: 10/08/25 | C27: 45943 | D27: CL560 | E27: Montpellier | F27: AG10 | G27: C28 | H27: P016 | I27: 2 | J27: 179 | K27: 0 | L27: 358 | M27: TRUE | N27: Date au format inconnu
A28: C-10769 | B28: 11/07/25 | C28: 45972 | D28: CL408 | E28: Montreuil | F28: AG03 | G28: C09 | H28: P030 | I28: 5 | J28: 18.5 | K28: 0 | L28: 92.5 | M28: TRUE | N28: Date au format inconnu
A29: C-10782 | B29: 45974 | C29: 45967 | D29: CL326 | E29: Lyon | F29: AG11 | G29: C33 | H29: P018 | I29: 5 | J29: 219 | K29: 0 | L29: 1095 | M29: TRUE | N29: Livraison antérieure à la commande
A30: C-10805 | B30: 45981 | C30: 45986 | D30: CL368 | E30: Toulon | F30: AG09 | H30: P035 | I30: 1 | J30: 120 | K30: 0.02 | L30: 117.6 | M30: TRUE | N30: Commercial non renseigné
A31: C-10838 | B31: 12/01/25 | C31: 45994 | D31: CL301 | E31: Colmar | F31: AG12 | G31: C36 | H31: P017 | I31: 4 | J31: 289 | K31: 0 | L31: 1156 | M31: TRUE | N31: Date au format inconnu
A32: C-10860 | B32: 46001 | C32: 45999 | D32: CL111 | E32: Paris | F32: AG03 | G32: C07 | H32: P002 | I32: 4 | J32: 649 | K32: 0 | L32: 2596 | M32: TRUE | N32: Livraison antérieure à la commande
A33: C-10895 | B33: 46013 | C33: 46014 | D33: CL561 | E33: Bordeaux | F33: AG07 | G33: C21 | H33: P034 | I33: 5 | J33: 245 | K33: 0 | L33: 1225 | M33: TRUE | N33: Prix unitaire dix fois le prix catalogue
A34: C-10907 | B34: 46017 | C34: 46021 | D34: CL510 | E34: Douai | F34: AG01 | G34: C02 | H34: P047 | I34: 1 | J34: 165 | K34: 0.08 | L34: 151.8 | M34: TRUE | N34: Produit absent du référentiel
A35: C-10910 | B35: 46017 | C35: 46020 | D35: CL003 | E35: Colmar | F35: AG12 | G35: C35 | H35: P030 | I35: 5 | J35: 185 | K35: 0 | L35: 925 | M35: TRUE | N35: Prix unitaire dix fois le prix catalogue
A36: C-10923 | B36: 46023 | C36: 46024 | D36: CL270 | E36: Roubaix | F36: AG01 | H36: P004 | I36: 2 | J36: 79 | K36: 0 | L36: 158 | M36: TRUE | N36: Commercial non renseigné
A37: C-10930 | B37: 01/02/26 | C37: 46028 | D37: CL587 | E37: Rennes | F37: AG06 | G37: C17 | H37: P006 | I37: 1 | J37: 420 | K37: 0 | L37: 420 | M37: TRUE | N37: Date au format inconnu
A38: C-10939 | B38: 46030 | C38: 46029 | D38: CL412 | E38: Vénissieux | F38: AG11 | G38: C32 | H38: P026 | I38: 5 | J38: 14.9 | K38: 0.02 | L38: 73.01 | M38: TRUE | N38: Livraison antérieure à la commande
A39: C-10957 | B39: 46038 | C39: 46035 | D39: CL430 | E39: Roubaix | F39: AG01 | G39: C03 | H39: P035 | I39: 3 | J39: 120 | K39: 0 | L39: 360 | M39: TRUE | N39: Livraison antérieure à la commande
A40: C-11052 | B40: 46071 | C40: 46078 | D40: CL557 | E40: Toulon | F40: AG09 | G40: C25 | H40: P051 | I40: 1 | J40: 69 | K40: 0.05 | L40: 65.55 | M40: TRUE | N40: Produit absent du référentiel
A41: C-11083 | B41: 46084 | C41: 46090 | D41: CL293 | E41: Saint-Nazaire | F41: AG05 | H41: P030 | I41: 10 | J41: 18.5 | K41: 0 | L41: 185 | M41: TRUE | N41: Commercial non renseigné
A42: C-11085 | B42: 46084 | C42: 46087 | D42: CL148 | E42: Toulouse | F42: AG08 | G42: C22 | H42: P047 | I42: 1 | J42: 245 | K42: 0 | L42: 245 | M42: TRUE | N42: Produit absent du référentiel
A43: C-11094 | B43: 03/06/26 | C43: 46092 | D43: CL562 | E43: Libourne | F43: AG07 | G43: C20 | H43: P032 | I43: 15 | J43: 22.9 | K43: 0 | L43: 343.5 | M43: TRUE | N43: Date au format inconnu
A44: C-11096 | B44: 03/09/26 | C44: 46093 | D44: CL352 | E44: Lille | F44: AG01 | G44: C02 | H44: P004 | I44: 3 | J44: 79 | K44: 0 | L44: 237 | M44: TRUE | N44: Date au format inconnu
A45: C-11103 | B45: 46092 | C45: 46099 | D45: CL010 | E45: Boulogne-Billancourt | F45: AG04 | G45: C11 | H45: P006 | I45: -2 | J45: 420 | K45: 0.05 | L45: -798 | M45: TRUE | N45: Quantité négative
A46: C-11150 | B46: 46107 | C46: 46104 | D46: CL443 | E46: Pessac | F46: AG07 | G46: C20 | H46: P009 | I46: 2 | J46: 245 | K46: 0.02 | L46: 480.2 | M46: TRUE | N46: Livraison antérieure à la commande
A47: C-11194 | B47: 46122 | C47: 46128 | D47: CL574 | E47: Nanterre | F47: AG04 | G47: C11 | H47: P051 | I47: 1 | J47: 149 | K47: 0.05 | L47: 141.55 | M47: TRUE | N47: Produit absent du référentiel
A48: C-11196 | B48: 46125 | C48: 46129 | D48: CL183 | E48: Vincennes | F48: AG03 | G48: C07 | H48: P017 | I48: -3 | J48: 289 | K48: 0.02 | L48: -849.66 | M48: TRUE | N48: Quantité négative
A49: C-11238 | B49: 46140 | C49: 46136 | D49: CL282 | E49: Montpellier | F49: AG10 | G49: C30 | H49: P011 | I49: 3 | J49: 310 | K49: 0.02 | L49: 911.4 | M49: TRUE | N49: Livraison antérieure à la commande
A50: C-11240 | B50: 46141 | C50: 46147 | D50: CL068 | E50: Douai | F50: AG01 | G50: C03 | H50: P040 | I50: -3 | J50: 180 | K50: 0 | L50: -540 | M50: TRUE | N50: Quantité négative
A51: C-11248 | B51: 46143 | C51: 46147 | D51: CL388 | E51: Nanterre | F51: AG04 | H51: P015 | I51: 2 | J51: 790 | K51: 0 | L51: 1580 | M51: TRUE | N51: Commercial non renseigné
A52: C-11292 | B52: 46161 | C52: 46154 | D52: CL213 | E52: Lille | F52: AG01 | G52: C03 | H52: P012 | I52: 6 | J52: 49 | K52: 0.08 | L52: 270.48 | M52: TRUE | N52: Livraison antérieure à la commande
A53: C-11305 | B53: 46164 | C53: 46168 | D53: CL431 | E53: Aubagne | F53: AG09 | H53: P020 | I53: 1 | J53: 790 | K53: 0.22 | L53: 616.2 | M53: TRUE | N53: Commercial non renseigné
A54: C-11325 | B54: 46174 | C54: 46176 | D54: CL502 | E54: Toulouse | F54: AG08 | G54: C24 | H54: P051 | I54: 15 | J54: 24.5 | K54: 0.02 | L54: 360.15 | M54: TRUE | N54: Produit absent du référentiel
A55: C-11423 | B55: 46212 | C55: 46216 | D55: CL106 | E55: Versailles | F55: AG04 | H55: P021 | I55: 2 | J55: 69 | K55: 0 | L55: 138 | M55: TRUE | N55: Commercial non renseigné
A56: C-11426 | B56: 46212 | C56: 46216 | D56: CL163 | E56: Blagnac | F56: AG08 | G56: C23 | H56: P034 | I56: -3 | J56: 24.5 | K56: 0.02 | L56: -72.03 | M56: TRUE | N56: Quantité négative
A57: C-11443 | B57: 46220 | C57: 46225 | D57: CL422 | E57: Courbevoie | F57: AG04 | G57: C11 | H57: P026 | I57: 15 | J57: 149 | K57: 0 | L57: 2235 | M57: TRUE | N57: Prix unitaire dix fois le prix catalogue
A58: C-11481 | B58: 08/04/26 | C58: 46241 | D58: CL276 | E58: Tourcoing | F58: AG01 | G58: C02 | H58: P008 | I58: 6 | J58: 129 | K58: 0.1 | L58: 696.6 | M58: TRUE | N58: Date au format inconnu
A59: C-11500 | B59: 46245 | C59: 46248 | D59: CL596 | E59: Saint-Étienne | F59: AG11 | G59: C33 | H59: P033 | I59: -3 | J59: 16.8 | K59: 0.05 | L59: -47.88 | M59: TRUE | N59: Quantité négative
A60: C-11512 | B60: 46251 | C60: 46262 | D60: CL221 | E60: Strasbourg | F60: AG12 | H60: P039 | I60: 1 | J60: 55 | K60: 0 | L60: 55 | M60: TRUE | N60: Commercial non renseigné
A61: C-11544 | B61: 46266 | C61: 46272 | D61: CL393 | E61: Marseille | F61: AG09 | G61: C27 | H61: P051 | I61: 1 | J61: 149 | K61: 0.02 | L61: 146.02 | M61: TRUE | N61: Produit absent du référentiel

Sheet Clients
A1: client_id | B1: raison_sociale | C1: ville | D1: secteur | E1: date_premiere_commande | F1: doublon_probable
A2: CL001 | B2: Nicolas Assurances | C2: Rennes | D2: Services | E2: 44439
A3: CL002 | B3: Duval Événements | C3: Lille | D3: Services | E3: 42387
A4: CL003 | B4: Denis Immobilier | C4: Colmar | D4: Services | E4: 45890
A5: CL004 | B5: Barbier Ingénierie | C5: Bordeaux | D5: Industrie | E5: 46141
A6: CL005 | B6: Nicolas Événements | C6: Roubaix | D6: Services | E6: 44277
A7: CL006 | B7: Legrand Événements | C7: Angers | D7: Services | E7: 44949
A8: CL007 | B8: Moreau Services | C8: Blagnac | D8: Services | E8: 43339
A9: CL008 | B9: Simon Assurances | C9: Paris | D9: Services | E9: 44074
A10: CL009 | B10: Mercier Événements | C10: Martigues | D10: Services | E10: 43157
A11: CL010 | B11: Boyer Distribution | C11: Boulogne-Billancourt | D11: Commerce | E11: 41036
A12: CL011 | B12: Garcia Architecture | C12: Toulon | D12: BTP | E12: 43284
A13: CL012 | B13: Vincent Assurances | C13: Versailles | D13: Services | E13: 43154
... A50: CL049 | B50: Roux Santé | C50: Nantes | D50: Santé | E50: 45667
A51: CL050 | B51: Mathieu Distribution | C51: Nanterre | D51: Commerce | E51: 41880 | F51: CL504
A52: CL051 | B52: Laurent Transports | C52: Martigues | D52: Transport | E52: 41841
A53: CL052 | B53: Lemaire Distribution | C53: Marseille | D53: Commerce | E53: 42138
A54: CL053 | B54: Robert Distribution | C54: Nanterre | D54: Commerce | E54: 41764
A55: CL054 | B55: Morin Architecture | C55: Montpellier | D55: BTP | E55: 45693
A56: CL055 | B56: David Transports | C56: Évreux | D56: Transport | E56: 45295
A57: CL056 | B57: David Architecture | C57: Tourcoing | D57: BTP | E57: 46031
A58: CL057 | B58: Thomas Ingénierie | C58: Cholet | D58: Industrie | E58: 43507
A59: CL058 | B59: Lefebvre Bâtiment | C59: Montpellier | D59: BTP | E59: 43444
A60: CL059 | B60: Vincent Santé | C60: Béziers | D60: Santé | E60: 46239
A61: CL060 | B61: Roux Immobilier | C61: Nîmes | D61: Services | E61: 46209
A62: CL061 | B62: François Assurances | C62: Créteil | D62: Services | E62: 42954 | F62: CL145
A63: CL062 | B63: Henry Distribution | C63: Vannes | D63: Commerce | E63: 43530
A64: CL063 | B64: Legrand Architecture | C64: Rennes | D64: BTP | E64: 45749
A65: CL064 | B65: Nicolas Transports | C65: Strasbourg | D65: Transport | E65: 43959
A66: CL065 | B66: Martin Architecture | C66: Montauban | D66: BTP | E66: 41144
A67: CL066 | B67: Thomas Architecture | C67: Colomiers | D67: BTP | E67: 44391
A68: CL067 | B68: Lefebvre Événements | C68: Paris | D68: Services | E68: 42719
A69: CL068 | B69: Bernard Conseil | C69: Douai | D69: Services | E69: 45804
A70: CL069 | B70: Denis Assurances | C70: Rouen | D70: Services | E70: 42653
A71: CL070 | B71: Robert Transports | C71: Lyon | D71: Transport | E71: 42702
A72: CL071 | B72: Robin Santé | C72: Montauban | D72: Santé | E72: 42388
A73: CL072 | B73: Henry Transports | C73: Montreuil | D73: Transport | E73: 43059
A74: CL073 | B74: Barbier Services | C74: Villeurbanne | D74: Services | E74: 45679
... A145: CL144 | B145: Mathieu Transports | C145: Lille | D145: Transport | E145: 42163
A146: CL145 | B146: François Assurances | C146: Créteil | D146: Services | E146: 45737 | F146: CL061
A147: CL146 | B147: Legrand Logistique | C147: Bordeaux | D147: Transport | E147: 44740
A148: CL147 | B148: Martin Logistique | C148: Montauban | D148: Transport | E148: 45994
A149: CL148 | B149: Duval Services | C149: Toulouse | D149: Services | E149: 41589
A150: CL149 | B150: Fournier Distribution | C150: Rouen | D150: Commerce | E150: 45713
A151: CL150 | B151: Petit Transports | C151: Marseille | D151: Transport | E151: 42375
A152: CL151 | B152: Robert Assurances | C152: Courbevoie | D152: Services | E152: 42542
A153: CL152 | B153: Roussel Architecture | C153: Cholet | D153: BTP | E153: 42367
A154: CL153 | B154: Roussel Immobilier | C154: Lyon | D154: Services | E154: 44886
A155: CL154 | B155: Lambert Services | C155: Créteil | D155: Services | E155: 44587
A156: CL155 | B156: Roux Transports | C156: Nantes | D156: Transport | E156: 42977
A157: CL156 | B157: Masson Distribution | C157: Libourne | D157: Commerce | E157: 43094
A158: CL157 | B158: David Industrie | C158: Libourne | D158: Industrie | E158: 45743
... A247: CL246 | B247: Durand Distribution | C247: Colmar | D247: Commerce | E247: 41135
A248: CL247 | B248: Perrin Architecture | C248: Saint-Étienne | D248: BTP | E248: 44557 | F248: CL277
A249: CL248 | B249: Roux Conseil | C249: Marseille | D249: Services | E249: 44096
A250: CL249 | B250: Moreau Santé | C250: Rouen | D250: Santé | E250: 43377
A251: CL250 | B251: Blanc Architecture | C251: Paris | D251: BTP | E251: 43689
A252: CL251 | B252: Rousseau Événements | C252: Toulouse | D252: Services | E252: 42159
A253: CL252 | B253: Leroy Bâtiment | C253: Rennes | D253: BTP | E253: 42537
A254: CL253 | B254: Clément Immobilier | C254: Dieppe | D254: Services | E254: 44319
A255: CL254 | B255: Petit Logistique | C255: Dieppe | D255: Transport | E255: 41274
A256: CL255 | B256: Marchand Conseil | C256: Lyon | D256: Services | E256: 42611
A257: CL256 | B257: Nicolas Bâtiment | C257: Montpellier | D257: BTP | E257: 43999
A258: CL257 | B258: Guérin Distribution | C258: Nantes | D258: Commerce | E258: 45607
A259: CL258 | B259: Fournier Industrie | C259: Bordeaux | D259: Industrie | E259: 45701
A260: CL259 | B260: Lemaire Services | C260: Colomiers | D260: Services | E260: 42506
... A277: CL276 | B277: Robert Services | C277: Tourcoing | D277: Services | E277: 44515
A278: CL277 | B278: Perrin Architecture | C278: Saint-Étienne | D278: BTP | E278: 45860 | F278: CL247
A279: CL278 | B279: Bertrand Assurances | C279: Montauban | D279: Services | E279: 43157
A280: CL279 | B280: Laurent Architecture | C280: Bordeaux | D280: BTP | E280: 43129
A281: CL280 | B281: Garnier Logistique | C281: Toulon | D281: Transport | E281: 42093
A282: CL281 | B282: Bertrand Événements | C282: Strasbourg | D282: Services | E282: 41134
A283: CL282 | B283: Clément Événements | C283: Montpellier | D283: Services | E283: 42692
A284: CL283 | B284: Robin Immobilier | C284: Fougères | D284: Services | E284: 42522
A285: CL284 | B285: Bertrand Santé | C285: Marseille | D285: Santé | E285: 44768
A286: CL285 | B286: Vincent Architecture | C286: Évreux | D286: BTP | E286: 43193
A287: CL286 | B287: Lambert Bâtiment | C287: Vincennes | D287: BTP | E287: 42055
A288: CL287 | B288: Mercier Bâtiment | C288: Strasbourg | D288: BTP | E288: 42919
A289: CL288 | B289: Robert Conseil | C289: Rouen | D289: Services | E289: 44123
A290: CL289 | B290: Garcia Industrie | C290: Cholet | D290: Industrie | E290: 45930
... A405: CL404 | B405: Fontaine Événements | C405: Courbevoie | D405: Services | E405: 41827
A406: CL405 | B406: Clément Ingénierie | C406: Montpellier | D406: Industrie | E406: 46072 | F406: CL421
A407: CL406 | B407: Guérin Logistique | C407: Toulouse | D407: Transport | E407: 45350
A408: CL407 | B408: Clément Industrie | C408: Bordeaux | D408: Industrie | E408: 42522
A409: CL408 | B409: Clément Services | C409: Montreuil | D409: Services | E409: 42443
A410: CL409 | B410: Moreau Assurances | C410: Paris | D410: Services | E410: 43228
A411: CL410 | B411: Fournier Assurances | C411: Bordeaux | D411: Services | E411: 43326
A412: CL411 | B412: Mercier Architecture | C412: Lyon | D412: BTP | E412: 41179
A413: CL412 | B413: Girard Industrie | C413: Vénissieux | D413: Industrie | E413: 41957
A414: CL413 | B414: Dupont Bureautique | C414: Bordeaux | D414: Commerce | E414: 45834
A415: CL414 | B415: Mathieu Industrie | C415: Boulogne-Billancourt | D415: Industrie | E415: 46260
A416: CL415 | B416: Guérin Immobilier | C416: Lyon | D416: Services | E416: 45524
A417: CL416 | B417: Boyer Transports | C417: Montpellier | D417: Transport | E417: 44938
A418: CL417 | B418: Garnier Santé | C418: Lyon | D418: Santé | E418: 41883
... A421: CL420 | B421: Laurent Assurances | C421: Rouen | D421: Services | E421: 43616
A422: CL421 | B422: Clément Ingénierie | C422: Montpellier | D422: Industrie | E422: 41029 | F422: CL405
A423: CL422 | B423: Vincent Événements | C423: Courbevoie | D423: Services | E423: 40910
A424: CL423 | B424: Legrand Ingénierie | C424: Montpellier | D424: Industrie | E424: 44909
A425: CL424 | B425: Simon Immobilier | C425: Nanterre | D425: Services | E425: 42549
A426: CL425 | B426: Nicolas Immobilier | C426: Évreux | D426: Services | E426: 42045
...

Sheet Produits
A1: produit_id | B1: libelle | C1: categorie | D1: prix_catalogue_ht | E1: cout_unitaire
A2: P001 | B2: Bureau droit 140 cm | C2: Mobilier | D2: 289 | E2: 193.63
A3: P002 | B3: Bureau réglable en hauteur | C3: Mobilier | D3: 649 | E3: 408.87
A4: P003 | B4: Fauteuil ergonomique | C4: Mobilier | D4: 359 | E4: 204.63
A5: P004 | B5: Chaise visiteur | C5: Mobilier | D5: 79 | E5: 46.61
A6: P005 | B6: Table de réunion 8 places | C6: Mobilier | D6: 890 | E6: 596.3
A7: P006 | B7: Armoire haute à portes | C7: Mobilier | D7: 420 | E7: 243.6
A8: P007 | B8: Caisson mobile 3 tiroirs | C8: Mobilier | D8: 165 | E8: 107.25
A9: P008 | B9: Étagère métallique | C9: Mobilier | D9: 129 | E9: 86.43
A10: P009 | B10: Cloison acoustique | C10: Mobilier | D10: 245 | E10: 164.15
A11: P010 | B11: Banque d’accueil | C11: Mobilier | D11: 1150 | E11: 713
A12: P011 | B12: Vestiaire 2 portes | C12: Mobilier | D12: 310 | E12: 186
A13: P012 | B13: Lampe de bureau LED | C13: Mobilier | D13: 49 | E13: 28.42
... A41: P040 | B41: Reprise et recyclage du matériel | C41: Maintenance | D41: 180 | E41: 82.8

Sheet Agences
A1: agence_id | B1: ville | C1: region | D1: responsable
A2: AG01 | B2: Lille | C2: Nord | D2: Claire Vasseur
A3: AG02 | B3: Rouen | C3: Nord | D3: Julien Lemoine
A4: AG03 | B4: Paris-Est | C4: Île-de-France | D4: Sonia Haddad
A5: AG04 | B5: Paris-Ouest | C5: Île-de-France | D5: Marc Delaunay
A6: AG05 | B6: Nantes | C6: Ouest | D6: Élodie Brunet
A7: AG06 | B7: Rennes | C7: Ouest | D7: Yann Le Goff
A8: AG07 | B8: Bordeaux | C8: Sud-Ouest | D8: Inès Lacaze
A9: AG08 | B9: Toulouse | C9: Sud-Ouest | D9: Thomas Ribeiro
A10: AG09 | B10: Marseille | C10: Méditerranée | D10: Karim Benali
A11: AG10 | B11: Montpellier | C11: Méditerranée | D11: Laure Fabre
A12: AG11 | B12: Lyon | C12: Est | D12: Nicolas Perret
A13: AG12 | B13: Strasbourg | C13: Est | D13: Anne Schmitt

Sheet Objectifs
A1: agence_id | B1: mois | C1: objectif_ca_ht
A2: AG01 | B2: 45658 | C2: 4600
A3: AG01 | B3: 45689 | C3: 5500
A4: AG01 | B4: 45717 | C4: 6000
A5: AG01 | B5: 45748 | C5: 5200
A6: AG01 | B6: 45778 | C6: 4800
A7: AG01 | B7: 45809 | C7: 5700
A8: AG01 | B8: 45839 | C8: 4800
A9: AG01 | B9: 45870 | C9: 3200
A10: AG01 | B10: 45901 | C10: 5500
A11: AG01 | B11: 45931 | C11: 5900
A12: AG01 | B12: 45962 | C12: 6000
A13: AG01 | B13: 45992 | C13: 6700
... A253: AG12 | B253: 46266 | C253: 5100
